phyex1d/__init__.py
phyex1d/cli.py
phyex1d/grid.py
phyex1d/phyex1d.py
phyex1d/physics.py
phyex1d/grids/L90arome.grid
phyex1d/grids/L90arome_reversed.grid
phyex1d/grids/L90mesonh.grid
phyex1d/grids/L90mesonh_reversed.grid
phyex1d/grids/README
phyex1d/namelists/default.namel
phyex1d-0.0.1.dist-info/licenses/LICENCE-fr.txt
phyex1d-0.0.1.dist-info/licenses/LICENSE-en.txt
phyex1d-0.0.1.dist-info/METADATA
phyex1d-0.0.1.dist-info/WHEEL
phyex1d-0.0.1.dist-info/entry_points.txt
phyex1d-0.0.1.dist-info/top_level.txt
phyex1d-0.0.1.dist-info/RECORD
