Metadata-Version: 2.4
Name: phyex1d
Version: 0.0.1
Summary: 1D model using PHYEX
Author-email: Sébastien Riette <sebastien.riette@meteo.fr>
License: CECILL-C
Classifier: Programming Language :: Python :: 3
Classifier: License :: CeCILL-C Free Software License Agreement (CECILL-C)
Classifier: Operating System :: POSIX :: Linux
Requires-Python: >=3.10
License-File: LICENCE-fr.txt
License-File: LICENSE-en.txt
Requires-Dist: pppy
Requires-Dist: ctypesForFortran
Requires-Dist: numpy
Requires-Dist: scipy
Requires-Dist: netCDF4
Requires-Dist: f90nml
Dynamic: license-file
